dos_like/__init__.py
dos_like/_dos.pyd
dos_like/build.py
dos_like/cp437.py
dos_like/dos.py
dos_like/int_with_flags.py
dos_like/runner.py
python_dos_like-0.0.4.dist-info/LICENSE
python_dos_like-0.0.4.dist-info/METADATA
python_dos_like-0.0.4.dist-info/WHEEL
python_dos_like-0.0.4.dist-info/top_level.txt
python_dos_like-0.0.4.dist-info/RECORD
