Metadata-Version: 2.1
Name: python-dos-like
Version: 0.0.4
Summary: Python bindings for the dos-like programming library
Home-page: https://github.com/cknave/python-dos-like
Author: kvance
Author-email: kvance@kvance.com
Classifier: Development Status :: 3 - Alpha
Classifier: Intended Audience :: Developers
Classifier: License :: OSI Approved :: MIT License
Classifier: Natural Language :: English
Classifier: Programming Language :: Python :: 3.9
Classifier: Programming Language :: Python :: 3.10
Classifier: Topic :: Software Development :: Libraries
Provides-Extra: dev
License-File: LICENSE
